README.md
setup.py
Andencento.egg-info/PKG-INFO
Andencento.egg-info/SOURCES.txt
Andencento.egg-info/dependency_links.txt
Andencento.egg-info/requires.txt
Andencento.egg-info/top_level.txt
userbot/AndencentoConfig.py
userbot/__init__.py
userbot/__main__.py
userbot/cmdhelp.py
userbot/config.py
userbot/var.py
userbot/assistant_utils/__init__.py
userbot/assistant_utils/decorators.py
userbot/cache/__init__.py
userbot/config/__init__.py
userbot/config/config.py
userbot/config/var.py
userbot/helpers/Fast.py
userbot/helpers/__init__.py
userbot/helpers/converter.py
userbot/helpers/devs.py
userbot/helpers/exceptions.py
userbot/helpers/fasttelethon.py
userbot/helpers/func.py
userbot/helpers/functions.py
userbot/helpers/google_image.py
userbot/helpers/image.py
userbot/helpers/jwatch.py
userbot/helpers/mmf.py
userbot/helpers/pranks.py
userbot/helpers/progress.py
userbot/helpers/runner.py
userbot/helpers/tools.py
userbot/helpers/tweet.py
userbot/helpers/videos.py
userbot/random_strings/__init__.py
userbot/random_strings/fun_str.py
userbot/random_strings/meme_str.py
userbot/random_strings/quotes.py
userbot/random_strings/rands.py
userbot/resources/__init__.py
userbot/session/__init__.py
userbot/session/main.py
userbot/session/session.py
userbot/utils/__init__.py
userbot/utils/assistant_load.py
userbot/utils/cmds.py
userbot/utils/decorators.py
userbot/utils/errors.py
userbot/utils/extras.py
userbot/utils/funcs.py
userbot/utils/main.py
userbot/utils/modules.py