Metadata-Version: 2.1
Name: Andencento
Version: 0.12
Summary: A Secure  and Powerful Python-Telethon Based Library For Andencento Userbot.
Home-page: https://github.com/Andencento/Andencento
Author: TeamAndencento
Author-email: paman7647@gmail.com
License: GNU AFFERO GENERAL PUBLIC LICENSE (v3)
Platform: UNKNOWN
Classifier: Programming Language :: Python :: 3
Classifier: License :: OSI Approved :: GNU General Public License v3 (GPLv3)
Classifier: Operating System :: OS Independent
Requires-Python: >=3.6
